{
  "start_speed": 0.0,
  "end_speed": 0.0,
  "segments": [
    {
      "inverted": false,
      "stop_end": false,
      "path": [
        {
          "x": 0.037,
          "y": 1.491
        },
        {
          "x": 0.24,
          "y": 1.496
        },
        {
          "x": 0.825,
          "y": 0.903
        },
        {
          "x": 0.924,
          "y": 1.095
        }
      ],
      "constraints": {
        "velocity": 0.925,
        "accel": 3.048
      }
    },
    {
      "inverted": true,
      "stop_end": false,
      "path": [
        {
          "x": 0.924,
          "y": 1.095
        },
        {
          "x": 0.857,
          "y": 0.964
        },
        {
          "x": 0.722,
          "y": 0.735
        },
        {
          "x": 0.638,
          "y": 0.601
        }
      ],
      "constraints": {
        "velocity": 0.45,
        "accel": 3.048
      }
    },
    {
      "inverted": false,
      "stop_end": false,
      "path": [
        {
          "x": 0.638,
          "y": 0.601
        },
        {
          "x": 0.722,
          "y": 0.735
        },
        {
          "x": 1.006,
          "y": 0.788
        },
        {
          "x": 1.165,
          "y": 0.68
        }
      ],
      "constraints": {
        "velocity": 0.925,
        "accel": 3.048
      }
    },
    {
      "inverted": true,
      "stop_end": false,
      "path": [
        {
          "x": 1.165,
          "y": 0.68
        },
        {
          "x": 1.066,
          "y": 0.748
        },
        {
          "x": 1.079,
          "y": 0.897
        },
        {
          "x": 1.071,
          "y": 1.099
        }
      ],
      "constraints": {
        "velocity": 0.925,
        "accel": 3.048
      }
    },
    {
      "inverted": false,
      "stop_end": false,
      "path": [
        {
          "x": 1.071,
          "y": 1.099
        },
        {
          "x": 1.079,
          "y": 0.897
        },
        {
          "x": 1.071,
          "y": 0.535
        },
        {
          "x": 1.106,
          "y": 0.229
        }
      ],
      "constraints": {
        "velocity": 0.925,
        "accel": 3.048
      }
    },
    {
      "inverted": true,
      "stop_end": false,
      "path": [
        {
          "x": 1.106,
          "y": 0.229
        },
        {
          "x": 1.071,
          "y": 0.536
        },
        {
          "x": 0.45,
          "y": 0.55
        },
        {
          "x": 0.311,
          "y": 0.408
        }
      ],
      "constraints": {
        "velocity": 0.925,
        "accel": 3.048
      }
    }
  ],
  "commands": [
    {
      "t": 2.004,
      "name": "clamp"
    },
    {
      "t": 2.043,
      "name": "intakeGoal"
    }
  ]
}